README.md
setup.py
alibabacloud_credentials/__init__.py
alibabacloud_credentials/client.py
alibabacloud_credentials/credentials.py
alibabacloud_credentials/exceptions.py
alibabacloud_credentials/models.py
alibabacloud_credentials/providers.py
alibabacloud_credentials/utils/__init__.py
alibabacloud_credentials/utils/auth_constant.py
alibabacloud_credentials/utils/auth_util.py
alibabacloud_credentials/utils/parameter_helper.py
alibabacloud_credentials_py2.egg-info/PKG-INFO
alibabacloud_credentials_py2.egg-info/SOURCES.txt
alibabacloud_credentials_py2.egg-info/dependency_links.txt
alibabacloud_credentials_py2.egg-info/requires.txt
alibabacloud_credentials_py2.egg-info/top_level.txt